ek_scraper/__init__.py
ek_scraper/__main__.py
ek_scraper/cli.py
ek_scraper/config.py
ek_scraper/data_store.py
ek_scraper/error.py
ek_scraper/scraper.py
ek_scraper/notifications/__init__.py
ek_scraper/notifications/ntfy_sh.py
ek_scraper/notifications/pushover.py
ek_scraper-0.2.4.dist-info/METADATA
ek_scraper-0.2.4.dist-info/WHEEL
ek_scraper-0.2.4.dist-info/entry_points.txt
ek_scraper-0.2.4.dist-info/licenses/LICENSE
ek_scraper-0.2.4.dist-info/RECORD
