Metadata-Version: 2.4
Name: ek-scraper
Version: 0.2.4
Summary: Simple scraper for kleinanzeigen.de searches with notifications for new ads.
Project-URL: Homepage, https://github.com/jonasehrlich/ek-scraper
Project-URL: Repository, https://github.com/jonasehrlich/ek-scraper
Author-email: Jonas Ehrlich <jonas.ehrlich@gmail.com>
License-Expression: MIT
License-File: LICENSE
Keywords: kleinanzeigen.de,scraper
Classifier: Development Status :: 4 - Beta
Classifier: Environment :: Console
Classifier: License :: OSI Approved :: MIT License
Classifier: Operating System :: OS Independent
Classifier: Programming Language :: Python
Requires-Python: >=3.11
Requires-Dist: aiohttp>=3.13.0
Requires-Dist: beautifulsoup4>=4.14.2
Requires-Dist: lxml>=6.0.2
Requires-Dist: pydantic>=2.12.2
